miniseed2mat/__init__.py
miniseed2mat/miniseed2mat.py
miniseed2mat-0.1.7.dist-info/entry_points.txt
miniseed2mat-0.1.7.dist-info/WHEEL
miniseed2mat-0.1.7.dist-info/METADATA
miniseed2mat-0.1.7.dist-info/RECORD
